databroom/__init__.py
databroom/cli/__init__.py
databroom/cli/commands.py
databroom/cli/config.py
databroom/cli/main.py
databroom/cli/operations.py
databroom/cli/utils.py
databroom/core/__init__.py
databroom/core/broom.py
databroom/core/cleaning_ops.py
databroom/core/debug_logger.py
databroom/core/history_tracker.py
databroom/core/pipeline.py
databroom/core/pipeline_io.py
databroom/generators/__init__.py
databroom/generators/base.py
databroom/generators/templates/R_pipeline.R.j2
databroom/generators/templates/macros.j2
databroom/generators/templates/python_pipeline.py.j2
databroom/gui/__init__.py
databroom/gui/app.py
databroom/gui/app_backup.py
databroom-0.4.dist-info/licenses/LICENSE
databroom-0.4.dist-info/METADATA
databroom-0.4.dist-info/WHEEL
databroom-0.4.dist-info/entry_points.txt
databroom-0.4.dist-info/top_level.txt
databroom-0.4.dist-info/RECORD
