Metadata-Version: 2.4
Name: databroom
Version: 0.4
Summary: A cross-language DataFrame cleaning assistant with interactive GUI and one-click code export
Author-email: Oliver Lozano <onlozanoo@gmail.com>
Maintainer-email: Oliver Lozano <onlozanoo@gmail.com>
License: MIT
Project-URL: Homepage, https://github.com/onlozanoo/databroom
Project-URL: Documentation, https://github.com/onlozanoo/databroom/blob/main/README.md
Project-URL: Repository, https://github.com/onlozanoo/databroom
Project-URL: Issues, https://github.com/onlozanoo/databroom/issues
Project-URL: Changelog, https://github.com/onlozanoo/databroom/releases
Keywords: data-cleaning,pandas,streamlit,data-preprocessing,code-generation,gui,dataframe
Classifier: Development Status :: 4 - Beta
Classifier: Intended Audience :: Developers
Classifier: Intended Audience :: Science/Research
Classifier: License :: OSI Approved :: MIT License
Classifier: Programming Language :: Python :: 3
Classifier: Programming Language :: Python :: 3.8
Classifier: Programming Language :: Python :: 3.9
Classifier: Programming Language :: Python :: 3.10
Classifier: Programming Language :: Python :: 3.11
Classifier: Programming Language :: Python :: 3.12
Classifier: Topic :: Scientific/Engineering :: Information Analysis
Classifier: Topic :: Software Development :: Code Generators
Classifier: Topic :: Software Development :: Libraries :: Python Modules
Requires-Python: >=3.8
License-File: LICENSE
Requires-Dist: pandas>=1.3.0
Requires-Dist: numpy>=1.20.0
Requires-Dist: streamlit>=1.28.0
Requires-Dist: unidecode>=1.3.0
Requires-Dist: jinja2>=3.0.0
Requires-Dist: pathlib2>=2.3.0
Requires-Dist: typer>=0.7.0
Requires-Dist: rich>=12.0.0
Requires-Dist: openpyxl>=3.0.0
Requires-Dist: xlrd>=2.0.0
Provides-Extra: cli
Requires-Dist: pandas>=1.3.0; extra == "cli"
Requires-Dist: numpy>=1.20.0; extra == "cli"
Requires-Dist: unidecode>=1.3.0; extra == "cli"
Requires-Dist: jinja2>=3.0.0; extra == "cli"
Requires-Dist: pathlib2>=2.3.0; extra == "cli"
Requires-Dist: typer>=0.7.0; extra == "cli"
Requires-Dist: rich>=12.0.0; extra == "cli"
Requires-Dist: openpyxl>=3.0.0; extra == "cli"
Requires-Dist: xlrd>=2.0.0; extra == "cli"
Provides-Extra: gui
Requires-Dist: pandas>=1.3.0; extra == "gui"
Requires-Dist: numpy>=1.20.0; extra == "gui"
Requires-Dist: streamlit>=1.28.0; extra == "gui"
Requires-Dist: unidecode>=1.3.0; extra == "gui"
Requires-Dist: jinja2>=3.0.0; extra == "gui"
Requires-Dist: pathlib2>=2.3.0; extra == "gui"
Requires-Dist: openpyxl>=3.0.0; extra == "gui"
Requires-Dist: xlrd>=2.0.0; extra == "gui"
Dynamic: license-file
